snap_sync_cleanup/snap_sync_cleanup.py
snap_sync_cleanup-1.1.1.dist-info/entry_points.txt
snap_sync_cleanup-1.1.1.dist-info/LICENSE
snap_sync_cleanup-1.1.1.dist-info/WHEEL
snap_sync_cleanup-1.1.1.dist-info/METADATA
snap_sync_cleanup-1.1.1.dist-info/RECORD
