Metadata-Version: 2.1
Name: snap-sync-cleanup
Version: 1.1.1
Summary: Cleans up remote backups created by snap-sync.
Home-page: https://github.com/GodTamIt/snap-sync-cleanup
License: BSD-2-Clause
Author: Christopher Tam
Author-email: ohgodtamit@gmail.com
Requires-Python: >=3.6,<4.0
Classifier: License :: OSI Approved :: BSD License
Classifier: Programming Language :: Python :: 3
Classifier: Programming Language :: Python :: 3.10
Classifier: Programming Language :: Python :: 3.6
Classifier: Programming Language :: Python :: 3.7
Classifier: Programming Language :: Python :: 3.8
Classifier: Programming Language :: Python :: 3.9
Requires-Dist: colorlog (>=6.6.0,<7.0.0)
Project-URL: Repository, https://github.com/GodTamIt/snap-sync-cleanup
